Metadata-Version: 2.1
Name: vtam
Version: 0.2.0
Summary: VTAM - Validation and Taxonomic Assignation of Metabarcoding Data is a metabarcoding pipeline. The analysis starts from high throughput sequencing (HTS) data of amplicons of one or several metabarcoding markers and produces an amplicon sequence variant (ASV) table of validated variants assigned to taxonomic groups.
Home-page: https://vtam.readthedocs.io
Author: Aitor Gonzalez, Thomas Dechatre, Reda Mekdad, Emese Meglecz
Author-email: aitor.gonzalez@univ-amu.fr
License: MIT
Platform: UNKNOWN
Classifier: Development Status :: 4 - Beta
Classifier: Environment :: Console
Classifier: Intended Audience :: Science/Research
Classifier: License :: OSI Approved :: MIT License
Classifier: Programming Language :: Python
Classifier: Programming Language :: Python :: 3
Classifier: Programming Language :: Python :: 3.7
Classifier: Programming Language :: Python :: 3.8
Classifier: Programming Language :: Python :: 3.9
Classifier: Programming Language :: Python :: 3.10
Classifier: Programming Language :: Python :: 3 :: Only
Classifier: Topic :: Scientific/Engineering :: Bio-Informatics
Classifier: Topic :: Software Development
Classifier: Operating System :: POSIX :: Linux
Classifier: Operating System :: Microsoft :: Windows :: Windows 10
License-File: LICENSE.txt
